{
  "name": "Footer",
  "type": "footer",
  "sections": {
    "md-trustbar": {
      "type": "md-trustbar",
      "disabled": false,
      "settings": {
        "color_scheme": "scheme-1",
        "trust_item_1_title": "Präqualifizierter Anbieter",
        "trust_item_1_text": "Für Pflegehilfsmittel und Versorgungslösungen qualifiziert",
        "trust_1_icon": "shield",
        "trust_1_custom_icon": "",
        "trust_item_2_title": "Google Bewertungen",
        "trust_item_2_text": "Von Kunden bei Google bewertet",
        "trust_2_icon": "star",
        "trust_2_custom_icon": "",
        "trust_item_3_title": "Schneller Versand",
        "trust_item_3_text": "Versand mit UPS, Großmengen nach Absprache",
        "trust_3_icon": "truck",
        "trust_3_custom_icon": "",
        "trust_item_4_title": "Persönlicher B2B-Service",
        "trust_item_4_text": "Direktkontakt für Praxen, Pflege, Gewerbe und Wiederverkäufer",
        "trust_4_icon": "user",
        "trust_4_custom_icon": ""
      }
    },
    "footer": {
      "type": "footer",
      "disabled": false,
      "settings": {
        "color_scheme": "scheme-3",
        "show_logo": true,
        "company_description": "Ihr Partner für Hygieneartikel, Pflegebedarf und gewerbliche Versorgung.",
        "company_address": "Kieler Straße 407, 22525 Hamburg",
        "company_email": "info@medical-deal.de",
        "company_phone": "+49 176 72042448",
        "heading_assortment": "Sortiment",
        "menu_assortment": "",
        "heading_service": "Service",
        "menu_service": "",
        "heading_company": "Unternehmen",
        "menu_company": "",
        "heading_legal": "Rechtliches",
        "menu_legal": "",
        "show_payment_icons": true,
        "show_shipping_text": false,
        "shipping_text": "",
        "show_legal_disclaimer": false,
        "legal_disclaimer_text": ""
      }
    }
  },
  "order": [
    "md-trustbar",
    "footer"
  ]
}
